pdaqp/__init__.py
pdaqp/juliapkg.json
pdaqp/pdaqp.py
pdaqp/plot.py
pdaqp-0.6.7.dist-info/METADATA
pdaqp-0.6.7.dist-info/WHEEL
pdaqp-0.6.7.dist-info/licenses/LICENSE
pdaqp-0.6.7.dist-info/RECORD
