Metadata-Version: 2.4
Name: pdaqp
Version: 0.6.7
Summary: A multi-parametric quadratic programming solver
Project-URL: Homepage, https://github.com/darnstrom/pdaqp
Project-URL: Issues, https://github.com/darnstrom/pdaqp/issues
Author-email: Daniel Arnström <daniel.arnstrom@gmail.com>
License-File: LICENSE
Requires-Python: >=3.8
Requires-Dist: juliacall==0.9.26
Requires-Dist: numpy
Provides-Extra: plot
Requires-Dist: plotly; extra == 'plot'
